lahella_cli/__init__.py
lahella_cli/activity_diff.py
lahella_cli/auth_helper.py
lahella_cli/create_course.py
lahella_cli/download_activities.py
lahella_cli/field_mapping.py
lahella_cli/login.py
lahella_cli/sync_activities.py
lahella_cli/update_payload.py
lahella_cli-0.1.2.dist-info/WHEEL
lahella_cli-0.1.2.dist-info/entry_points.txt
lahella_cli-0.1.2.dist-info/METADATA
lahella_cli-0.1.2.dist-info/RECORD
