Metadata-Version: 2.4
Name: lahella-cli
Version: 0.1.2
Summary: CLI tool for managing Lähellä.fi activity listings via YAML
Author: Jouni Seppänen
Author-email: Jouni Seppänen <jks@iki.fi>
License-Expression: MIT
Classifier: Development Status :: 3 - Alpha
Classifier: Programming Language :: Python :: 3.14
Requires-Dist: filelock>=3.16.0
Requires-Dist: httpx>=0.28.1
Requires-Dist: playwright>=1.57.0
Requires-Dist: ruamel-yaml>=0.18.17
Requires-Python: >=3.14
Project-URL: Homepage, https://github.com/jkseppan/lahella-cli
Project-URL: Repository, https://github.com/jkseppan/lahella-cli
